LICENSE
README.md
setup.py
pierl/__init__.py
pierl/config.py
pierl/constants.py
pierl.egg-info/PKG-INFO
pierl.egg-info/SOURCES.txt
pierl.egg-info/dependency_links.txt
pierl.egg-info/requires.txt
pierl.egg-info/top_level.txt